[[{"xpath": "/html[1]/body[1]/div[2]/div[2]/canvas[1]", "css": "#distance canvas.marks", "startingPath": "-1", "siblings": "0", "event": "mousemove", "info": [ 455,  130]}, {"xpath": "/html[1]/body[1]/div[2]/div[2]/canvas[1]", "css": "#distance canvas.marks", "startingPath": "-1", "siblings": "0", "event": "mouseout", "info": [ 194,  -69]}, {"xpath": "/html[1]/body[1]/div[2]/div[4]/canvas[1]", "css": "#departure canvas.marks", "startingPath": "-1", "siblings": "0", "event": "mousemove", "info": [ 194,  151]}, {"xpath": "/html[1]/body[1]/div[2]/div[4]/canvas[1]", "css": "#departure canvas.marks", "startingPath": "-1", "siblings": "0", "event": "mousemove", "info": [ 266,  152]}, {"xpath": "/html[1]/body[1]/div[2]/div[4]/canvas[1]", "css": "#departure canvas.marks", "startingPath": "-1", "siblings": "0", "event": "brush", "info": [ 268,  50]}, {"xpath": "/html[1]/body[1]/div[2]/div[4]/canvas[1]", "css": "#departure canvas.marks", "startingPath": "-1", "siblings": "0", "event": "brush", "info": [[[268,50],[268,50]]]}, {"xpath": "/html[1]/body[1]/div[2]/div[4]/canvas[1]", "css": "#departure canvas.marks", "startingPath": "-1", "siblings": "0", "event": "click", "info": [ 268,  154]}, {"xpath": "/html[1]/body[1]/div[2]/div[4]/canvas[1]", "css": "#departure canvas.marks", "startingPath": "-1", "siblings": "0", "event": "mousemove", "info": [ 266,  152]}, {"xpath": "/html[1]/body[1]/div[2]/div[4]/canvas[1]", "css": "#departure canvas.marks", "startingPath": "-1", "siblings": "0", "event": "brush", "info": [ 268,  50]}, {"xpath": "/html[1]/body[1]/div[2]/div[4]/canvas[1]", "css": "#departure canvas.marks", "startingPath": "-1", "siblings": "0", "event": "brush", "info": [[[268,50],[268,50]]]}, {"xpath": "/html[1]/body[1]/div[2]/div[4]/canvas[1]", "css": "#departure canvas.marks", "startingPath": "-1", "siblings": "0", "event": "click", "info": [ 268,  154]}, {"xpath": "/html[1]/body[1]/div[2]/div[4]/canvas[1]", "css": "#departure canvas.marks", "startingPath": "-1", "siblings": "0", "event": "mousemove", "info": [ 272,  153]}, {"xpath": "/html[1]/body[1]/div[2]/div[4]/canvas[1]", "css": "#departure canvas.marks", "startingPath": "-1", "siblings": "0", "event": "brush", "info": [ 274,  50]}, {"xpath": "/html[1]/body[1]/div[2]/div[4]/canvas[1]", "css": "#departure canvas.marks", "startingPath": "-1", "siblings": "0", "event": "brush", "info": [[[274,50],[274,50]]]}, {"xpath": "/html[1]/body[1]/div[2]/div[4]/canvas[1]", "css": "#departure canvas.marks", "startingPath": "-1", "siblings": "0", "event": "click", "info": [ 274,  155]}, {"xpath": "/html[1]/body[1]/div[2]/div[4]/canvas[1]", "css": "#departure canvas.marks", "startingPath": "-1", "siblings": "0", "event": "mousemove", "info": [ 272,  153]}, {"xpath": "/html[1]/body[1]/div[2]/div[4]/canvas[1]", "css": "#departure canvas.marks", "startingPath": "-1", "siblings": "0", "event": "brush", "info": [ 274,  50]}, {"xpath": "/html[1]/body[1]/div[2]/div[4]/canvas[1]", "css": "#departure canvas.marks", "startingPath": "-1", "siblings": "0", "event": "brush", "info": [[[274,50],[274,50]]]}, {"xpath": "/html[1]/body[1]/div[2]/div[4]/canvas[1]", "css": "#departure canvas.marks", "startingPath": "-1", "siblings": "0", "event": "click", "info": [ 274,  155]}, {"xpath": "/html[1]/body[1]/div[2]/div[4]/canvas[1]", "css": "#departure canvas.marks", "startingPath": "-1", "siblings": "0", "event": "mousemove", "info": [ 276,  161]}, {"xpath": "/html[1]/body[1]/div[2]/div[4]/canvas[1]", "css": "#departure canvas.marks", "startingPath": "-1", "siblings": "0", "event": "brush", "info": [ 270,  50]}, {"xpath": "/html[1]/body[1]/div[2]/div[4]/canvas[1]", "css": "#departure canvas.marks", "startingPath": "-1", "siblings": "0", "event": "brush", "info": [[[278,50],[298,50]]]}, {"xpath": "/html[1]/body[1]/div[2]/div[4]/canvas[1]", "css": "#departure canvas.marks", "startingPath": "-1", "siblings": "0", "event": "brush", "info": [[[270,50],[278,50]]]}, {"xpath": "/html[1]/body[1]/div[2]/div[4]/canvas[1]", "css": "#departure canvas.marks", "startingPath": "-1", "siblings": "0", "event": "brush", "info": [[[270,50],[370,50]]]}, {"xpath": "/html[1]/body[1]/div[2]/div[4]/canvas[1]", "css": "#departure canvas.marks", "startingPath": "-1", "siblings": "0", "event": "mouseout", "info": [ 703,  215]}, {"xpath": "/html[1]/body[1]/div[2]/div[6]/canvas[1]", "css": "#airtime canvas.marks", "startingPath": "-1", "siblings": "0", "event": "mousemove", "info": [ 82,  13]}, {"xpath": "/html[1]/body[1]/div[2]/div[6]/canvas[1]", "css": "#airtime canvas.marks", "startingPath": "-1", "siblings": "0", "event": "mouseout", "info": [ 829,  -114]}],[ {"xpath": "/html[1]/body[1]/div[2]/div[6]/canvas[1]", "css": "#airtime canvas.marks", "startingPath": "-1", "siblings": "0", "event": "brush", "info": [[[270,50],[363,50]]]}, {"xpath": "/html[1]/body[1]/div[2]/div[6]/canvas[1]", "css": "#airtime canvas.marks", "startingPath": "-1", "siblings": "0", "event": "brush",  "info": [[[270,50],[360,50]],[[ 25,  0,  359,  168,0,0],[[0,0],[0,0]]]]}, {"xpath": "/html[1]/body[1]/div[2]/div[6]/canvas[1]", "css": "#airtime canvas.marks", "startingPath": "-1", "siblings": "0", "event": "brush", "info": [[[270,50],[384,50]]]}, {"xpath": "/html[1]/body[1]/div[2]/div[6]/canvas[1]", "css": "#airtime canvas.marks", "startingPath": "-1", "siblings": "0", "event": "mousemove", "info": [ 386,  108]}, {"xpath": "/html[1]/body[1]/div[2]/div[6]/canvas[1]", "css": "#airtime canvas.marks", "startingPath": "-1", "siblings": "0", "event": "brush", "info": [[[388,50],[504,50]]]}, {"xpath": "/html[1]/body[1]/div[2]/div[6]/canvas[1]", "css": "#airtime canvas.marks", "startingPath": "-1", "siblings": "0", "event": "mouseout", "info": [ 700,  55]}, {"xpath": "/html[1]/body[1]/div[2]/div[6]/canvas[1]", "css": "#airtime canvas.marks", "startingPath": "-1", "siblings": "0", "event": "mouseout", "info": [ 684,  71]}, {"xpath": "/html[1]/body[1]/div[2]/div[1]/canvas[1]", "css": "#count canvas.marks", "startingPath": "-1", "siblings": "0", "event": "mouseout", "info": [ 447,  94]}, {"xpath": "/html[1]/body[1]/div[2]/div[1]/canvas[1]", "css": "#count canvas.marks", "startingPath": "-1", "siblings": "0", "event": "mouseout", "info": [ 397,  -44]}, {"xpath": "/html[1]/body[1]/div[2]/div[6]/canvas[1]", "css": "#airtime canvas.marks", "startingPath": "-1", "siblings": "0", "event": "mousemove", "info": [ 506,  105]}, {"xpath": "/html[1]/body[1]/div[2]/div[6]/canvas[1]", "css": "#airtime canvas.marks", "startingPath": "-1", "siblings": "0", "event": "brush", "info": [[[504,50],[508,50]]]}, {"xpath": "/html[1]/body[1]/div[2]/div[6]/canvas[1]", "css": "#airtime canvas.marks", "startingPath": "-1", "siblings": "0", "event": "mousemove", "info": [ 501,  113]}, {"xpath": "/html[1]/body[1]/div[2]/div[6]/canvas[1]", "css": "#airtime canvas.marks", "startingPath": "-1", "siblings": "0", "event": "brush", "info": [ 503,  50]}, {"xpath": "/html[1]/body[1]/div[2]/div[6]/canvas[1]", "css": "#airtime canvas.marks", "startingPath": "-1", "siblings": "0", "event": "brush", "info": [[[503,50],[504,50]]]}, {"xpath": "/html[1]/body[1]/div[2]/div[6]/canvas[1]", "css": "#airtime canvas.marks", "startingPath": "-1", "siblings": "0", "event": "click", "info": [ 504,  116]}, {"xpath": "/html[1]/body[1]/div[2]/div[6]/canvas[1]", "css": "#airtime canvas.marks", "startingPath": "-1", "siblings": "0", "event": "mouseout", "info": [ 643,  213]}],[ {"xpath": "/html[1]/body[1]/div[2]/div[1]/canvas[1]", "css": "#count canvas.marks", "startingPath": "-1", "siblings": "0", "event": "mouseout", "info": [ 228,  -16]}, {"xpath": "/html[1]/body[1]/div[2]/div[1]/canvas[1]", "css": "#count canvas.marks", "startingPath": "-1", "siblings": "0", "event": "mouseout", "info": [ 92,  98]}]]